Metadata-Version: 2.1
Name: py2quantikz
Version: 0.0.3
Summary: Converts Quantum Circuit Code to quantikz Diagrams
Home-page: https://github.com/madhavan-raja/py2quantikz
Author: Madhavan Raja
Author-email: madhavanraja99@gmail.com
License: MIT
Keywords: python,tikz,quantikz,latex,quantum
Classifier: Programming Language :: Python :: 3
Classifier: License :: OSI Approved :: MIT License
Classifier: Operating System :: OS Independent
Requires-Python: >=3.6
License-File: LICENSE
